Workbook

Sheet PLANTILLA
C1: TOTALES | E1: =SUM(E3:E6987) -> 66427.31 | F1: =SUM(F3:F6987) -> 66427.31 | J1: =E1-F1 -> -3.3469405e-10 | AH1: NO INGRESAR DATOS EN ESTAS CELDAS
A2: Origen | B2: Num.Voucher | C2: Fecha de Liquidacion | D2: Cuenta | E2: Monto Debe | F2: Monto Haber | G2: Moneda S/D | H2: T.Cambio | I2: Doc | J2: Num.Doc | K2: Fec.Doc | L2: Fec.Ven | M2: RUC O DNI | N2: C.Costo | O2: Presupuesto | P2: F.Efectivo | Q2: Glosa | R2: Libro C/V/R | S2: Mto.Neto 1 | T2: Mto.Neto 2 | U2: Mto.Neto 3 | V2: Mto.Neto 4 | W2: Mto.Neto 5 | X2: Mto.Neto 6 | Y2: Mto.Neto 7 | Z2: Mto.Neto 8 | AA2: Mto.Neto 9 | AB2: Mto.IGV | AC2: Ref.Doc | AD2: Ref.Num.Doc | AE2: Ref.Fecha | AF2: Det.Num | AG2: Det.Fecha | AH2: RUC O DNI | AI2: R. Social | AJ2: Tipo | AK2: Tip.Doc.Iden | AL2: Medio de Pago | AM2: Apellido 1 | AN2: Apellido 2 | AO2: Nombre | AP2: T.Bien
A3: 15 | B3: 01 | C3: 46174 | D3: 14132 | F3: 500 | G3: S | H3: 3.417 | I3: PL | J3: 3626 | K3: 46167 | L3: 46167 | M3: 05387728 | Q3: MENDOZA/PUCALLPA-MOYOBAMBA-PUCALLPA/CKW767/EXCESO (0) | AH3: =M3 -> 05387728 | AI3: =IFERROR(INDEX(PROVEEDORES!$B$1:$B$6940,MATCH(AH3,PROVEEDORES!$A$1:$A$6940,0)),"") -> MENDOZA VARGAS RAUL
A4: 15 | B4: 01 | C4: 46174 | D4: 14132 | F4: 113.4 | G4: S | H4: 3.417 | I4: PL | J4: 3693 | K4: 46174 | L4: 46174 | M4: 05387728 | Q4: POR LIQUIDAR | AH4: =M4 -> 05387728 | AI4: =IFERROR(INDEX(PROVEEDORES!$B$1:$B$6940,MATCH(AH4,PROVEEDORES!$A$1:$A$6940,0)),"") -> MENDOZA VARGAS RAUL
A5: 15 | B5: 01 | C5: 46174 | D5: 42121 | E5: 52.2 | G5: S | H5: 3.417 | I5: 01 | J5: FH02-599324 | K5: 46172 | L5: 46172 | M5: 20511004251 | Q5: PEAJE | AH5: =M5 -> 20511004251 | AI5: =IFERROR(INDEX(PROVEEDORES!$B$1:$B$6940,MATCH(AH5,PROVEEDORES!$A$1:$A$6940,0)),"") -> CONCESIONARIA IIRSA NORTE S.A.
A6: 15 | B6: 01 | C6: 46174 | D6: 42121 | E6: 52.2 | G6: S | H6: 3.417 | I6: 01 | J6: FH01-511823 | K6: 46172 | L6: 46172 | M6: 20511004251 | Q6: PEAJE | AH6: =M6 -> 20511004251 | AI6: =IFERROR(INDEX(PROVEEDORES!$B$1:$B$6940,MATCH(AH6,PROVEEDORES!$A$1:$A$6940,0)),"") -> CONCESIONARIA IIRSA NORTE S.A.
A7: 15 | B7: 01 | C7: 46174 | D7: 42121 | E7: 20 | G7: S | H7: 3.417 | I7: 01 | J7: E001-3991 | K7: 46167 | L7: 46167 | M7: 10762857575 | Q7: AFLOJATODO | AH7: =M7 -> 10762857575 | AI7: =IFERROR(INDEX(PROVEEDORES!$B$1:$B$6940,MATCH(AH7,PROVEEDORES!$A$1:$A$6940,0)),"") -> FLORES HOYOS SIOMI LUCERO
A8: 15 | B8: 01 | C8: 46174 | D8: 42121 | E8: 40 | G8: S | H8: 3.417 | I8: 01 | J8: E001-240 | K8: 46174 | L8: 46174 | M8: 10713390793 | Q8: REPARACION DE LLANTA | AH8: =M8 -> 10713390793 | AI8: =IFERROR(INDEX(PROVEEDORES!$B$1:$B$6940,MATCH(AH8,PROVEEDORES!$A$1:$A$6940,0)),"") -> PADILLA MELENDEZ JOSE VALENTINO
A9: 15 | B9: 01 | C9: 46174 | D9: 42121 | E9: 40 | G9: S | H9: 3.417 | I9: 01 | J9: FF01-4607 | K9: 46174 | L9: 46174 | M9: 10755996551 | Q9: LAVADO | AH9: =M9 -> 10755996551 | AI9: =IFERROR(INDEX(PROVEEDORES!$B$1:$B$6940,MATCH(AH9,PROVEEDORES!$A$1:$A$6940,0)),"") -> PEREZ DAHUA FRANS DENNIS
A10: 15 | B10: 01 | C10: 46174 | D10: 42121 | E10: 49 | G10: S | H10: 3.417 | I10: 01 | J10: FF01-4609 | K10: 46174 | L10: 46174 | M10: 10755996551 | Q10: ARREGLO DE CARGA | AH10: =M10 -> 10755996551 | AI10: =IFERROR(INDEX(PROVEEDORES!$B$1:$B$6940,MATCH(AH10,PROVEEDORES!$A$1:$A$6940,0)),"") -> PEREZ DAHUA FRANS DENNIS
A11: 15 | B11: 01 | C11: 46174 | D11: 63433 | E11: 40 | G11: S | H11: 3.417 | I11: 03 | J11: 0001-000059 | K11: 46172 | L11: 46172 | M11: 10009448239 | Q11: REPARACION DE LLANTA | AH11: =M11 -> 10009448239 | AI11: =IFERROR(INDEX(PROVEEDORES!$B$1:$B$6940,MATCH(AH11,PROVEEDORES!$A$1:$A$6940,0)),"") -> LUNA PANDURO GUILLERMO
A12: 15 | B12: 01 | C12: 46174 | D12: 6314 | E12: 40 | G12: S | H12: 3.417 | I12: 03 | J12: 0001-043570 | K12: 46167 | L12: 46167 | M12: 10446876312 | Q12: CONSUMO | AH12: =M12 -> 10446876312 | AI12: =IFERROR(INDEX(PROVEEDORES!$B$1:$B$6940,MATCH(AH12,PROVEEDORES!$A$1:$A$6940,0)),"") -> IRENE ELENITH ROJAS RUIZ
A13: 15 | B13: 01 | C13: 46174 | D13: 6314 | E13: 40 | G13: S | H13: 3.417 | I13: 03 | J13: 0001-004202 | K13: 46168 | L13: 46168 | M13: 10414823080 | Q13: CONSUMO | AH13: =M13 -> 10414823080 | AI13: =IFERROR(INDEX(PROVEEDORES!$B$1:$B$6940,MATCH(AH13,PROVEEDORES!$A$1:$A$6940,0)),"") -> TOLENTINO SIMON REINA
A14: 15 | B14: 01 | C14: 46174 | D14: 6314 | E14: 40 | G14: S | H14: 3.417 | I14: 03 | J14: 0001-004210 | K14: 46169 | L14: 46169 | M14: 10414823080 | Q14: CONSUMO | AH14: =M14 -> 10414823080 | AI14: =IFERROR(INDEX(PROVEEDORES!$B$1:$B$6940,MATCH(AH14,PROVEEDORES!$A$1:$A$6940,0)),"") -> TOLENTINO SIMON REINA
A15: 15 | B15: 01 | C15: 46174 | D15: 6314 | E15: 40 | G15: S | H15: 3.417 | I15: 03 | J15: 0003-000507 | K15: 46170 | L15: 46170 | M15: 10804598184 | Q15: CONSUMO | AH15: =M15 -> 10804598184 | AI15: =IFERROR(INDEX(PROVEEDORES!$B$1:$B$6940,MATCH(AH15,PROVEEDORES!$A$1:$A$6940,0)),"") -> RODRIGUEZ SAAVEDRA VICTORIA
A16: 15 | B16: 01 | C16: 46174 | D16: 6314 | E16: 40 | G16: S | H16: 3.417 | I16: 03 | J16: 0002-001172 | K16: 46171 | L16: 46171 | M16: 10011321840 | Q16: CONSUMO | AH16: =M16 -> 10011321840 | AI16: =IFERROR(INDEX(PROVEEDORES!$B$1:$B$6940,MATCH(AH16,PROVEEDORES!$A$1:$A$6940,0)),"") -> PIRO RENGIFO GUILLERMO
A17: 15 | B17: 01 | C17: 46174 | D17: 6314 | E17: 40 | G17: S | H17: 3.417 | I17: 03 | J17: 0001-0004611 | K17: 46172 | L17: 46172 | M17: 10718880063 | Q17: CONSUMO | AH17: =M17 -> 10718880063 | AI17: =IFERROR(INDEX(PROVEEDORES!$B$1:$B$6940,MATCH(AH17,PROVEEDORES!$A$1:$A$6940,0)),"") -> DIAZ VILLALOBOS DIMAS
A18: 15 | B18: 01 | C18: 46174 | D18: 6314 | E18: 40 | G18: S | H18: 3.417 | I18: 03 | J18: 0003-000514 | K18: 46173 | L18: 46173 | M18: 10804598184 | Q18: CONSUMO | AH18: =M18 -> 10804598184 | AI18: =IFERROR(INDEX(PROVEEDORES!$B$1:$B$6940,MATCH(AH18,PROVEEDORES!$A$1:$A$6940,0)),"") -> RODRIGUEZ SAAVEDRA VICTORIA
A19: 15 | B19: 01 | C19: 46174 | D19: 6314 | E19: 40 | G19: S | H19: 3.417 | I19: 03 | J19: 0001-004224 | K19: 46174 | L19: 46174 | M19: 10414823080 | Q19: CONSUMO | AH19: =M19 -> 10414823080 | AI19: =IFERROR(INDEX(PROVEEDORES!$B$1:$B$6940,MATCH(AH19,PROVEEDORES!$A$1:$A$6940,0)),"") -> TOLENTINO SIMON REINA
A20: 15 | B20: 02 | C20: 46174 | D20: 14132 | F20: 750 | G20: S | H20: 3.417 | I20: PL | J20: 3598 | K20: 46163 | L20: 46163 | M20: 10499879 | Q20: VEGA/PUCALLPA-JAEN-PUCALLPA/CKW716/EXCESO (0) | AH20: =M20 -> 10499879 | AI20: =IFERROR(INDEX(PROVEEDORES!$B$1:$B$6940,MATCH(AH20,PROVEEDORES!$A$1:$A$6940,0)),"") -> VEGA JANAMPA HECTOR HUGO
A21: 15 | B21: 02 | C21: 46174 | D21: 14132 | F21: 80 | G21: S | H21: 3.417 | I21: PL | J21: 3651 | K21: 46170 | L21: 46170 | M21: 10499879 | Q21: POR LIQUIDAR | AH21: =M21 -> 10499879 | AI21: =IFERROR(INDEX(PROVEEDORES!$B$1:$B$6940,MATCH(AH21,PROVEEDORES!$A$1:$A$6940,0)),"") -> VEGA JANAMPA HECTOR HUGO
A22: 15 | B22: 02 | C22: 46174 | D22: 14132 | F22: 176.2 | G22: S | H22: 3.417 | I22: PL | J22: 3686 | K22: 46174 | L22: 46174 | M22: 10499879 | Q22: POR LIQUIDAR | AH22: =M22 -> 10499879 | AI22: =IFERROR(INDEX(PROVEEDORES!$B$1:$B$6940,MATCH(AH22,PROVEEDORES!$A$1:$A$6940,0)),"") -> VEGA JANAMPA HECTOR HUGO
A23: 15 | B23: 02 | C23: 46174 | D23: 42121 | E23: 52.2 | G23: S | H23: 3.417 | I23: 01 | J23: FH02-599022 | K23: 46170 | L23: 46170 | M23: 20511004251 | Q23: PEAJE | AH23: =M23 -> 20511004251 | AI23: =IFERROR(INDEX(PROVEEDORES!$B$1:$B$6940,MATCH(AH23,PROVEEDORES!$A$1:$A$6940,0)),"") -> CONCESIONARIA IIRSA NORTE S.A.
A24: 15 | B24: 02 | C24: 46174 | D24: 42121 | E24: 52.2 | G24: S | H24: 3.417 | I24: 01 | J24: FH01-511089 | K24: 46166 | L24: 46166 | M24: 20511004251 | Q24: PEAJE | AH24: =M24 -> 20511004251 | AI24: =IFERROR(INDEX(PROVEEDORES!$B$1:$B$6940,MATCH(AH24,PROVEEDORES!$A$1:$A$6940,0)),"") -> CONCESIONARIA IIRSA NORTE S.A.
A25: 15 | B25: 02 | C25: 46174 | D25: 42121 | E25: 52.2 | G25: S | H25: 3.417 | I25: 01 | J25: FG01-670519 | K25: 46166 | L25: 46166 | M25: 20511004251 | Q25: PEAJE | AH25: =M25 -> 20511004251 | AI25: =IFERROR(INDEX(PROVEEDORES!$B$1:$B$6940,MATCH(AH25,PROVEEDORES!$A$1:$A$6940,0)),"") -> CONCESIONARIA IIRSA NORTE S.A.
A26: 15 | B26: 02 | C26: 46174 | D26: 42121 | E26: 52.2 | G26: S | H26: 3.417 | I26: 01 | J26: FE01-1273127 | K26: 46167 | L26: 46167 | M26: 20511004251 | Q26: PEAJE | AH26: =M26 -> 20511004251 | AI26: =IFERROR(INDEX(PROVEEDORES!$B$1:$B$6940,MATCH(AH26,PROVEEDORES!$A$1:$A$6940,0)),"") -> CONCESIONARIA IIRSA NORTE S.A.
A27: 15 | B27: 02 | C27: 46174 | D27: 42121 | E27: 52.2 | G27: S | H27: 3.417 | I27: 01 | J27: FF01-793241 | K27: 46167 | L27: 46167 | M27: 20511004251 | Q27: PEAJE | AH27: =M27 -> 20511004251 | AI27: =IFERROR(INDEX(PROVEEDORES!$B$1:$B$6940,MATCH(AH27,PROVEEDORES!$A$1:$A$6940,0)),"") -> CONCESIONARIA IIRSA NORTE S.A.
A28: 15 | B28: 02 | C28: 46174 | D28: 42121 | E28: 52.2 | G28: S | H28: 3.417 | I28: 01 | J28: FG02-684003 | K28: 46167 | L28: 46167 | M28: 20511004251 | Q28: PEAJE | AH28: =M28 -> 20511004251 | AI28: =IFERROR(INDEX(PROVEEDORES!$B$1:$B$6940,MATCH(AH28,PROVEEDORES!$A$1:$A$6940,0)),"") -> CONCESIONARIA IIRSA NORTE S.A.
A29: 15 | B29: 02 | C29: 46174 | D29: 42121 | E29: 30 | G29: S | H29: 3.417 | I29: 01 | J29: E001-2079 | K29: 46168 | L29: 46168 | M29: 10413807927 | Q29: ALOJAMIENTO | AH29: =M29 -> 10413807927 | AI29: =IFERROR(INDEX(PROVEEDORES!$B$1:$B$6940,MATCH(AH29,PROVEEDORES!$A$1:$A$6940,0)),"") -> REVILLA FUENTES JANETH MILENA
A30: 15 | B30: 02 | C30: 46174 | D30: 42121 | E30: 50 | G30: S | H30: 3.417 | I30: 01 | J30: E001-4181 | K30: 46170 | L30: 46170 | M30: 10439041701 | Q30: REPARACION DE LLANTA | AH30: =M30 -> 10439041701 | AI30: =IFERROR(INDEX(PROVEEDORES!$B$1:$B$6940,MATCH(AH30,PROVEEDORES!$A$1:$A$6940,0)),"") -> GUERRA SALAS ROMER
A31: 15 | B31: 02 | C31: 46174 | D31: 42121 | E31: 40 | G31: S | H31: 3.417 | I31: 01 | J31: FF01-4597 | K31: 46173 | L31: 46173 | M31: 10755996551 | Q31: LAVADO | AH31: =M31 -> 10755996551 | AI31: =IFERROR(INDEX(PROVEEDORES!$B$1:$B$6940,MATCH(AH31,PROVEEDORES!$A$1:$A$6940,0)),"") -> PEREZ DAHUA FRANS DENNIS
A32: 15 | B32: 02 | C32: 46174 | D32: 42121 | E32: 53 | G32: S | H32: 3.417 | I32: 01 | J32: FF01-4598 | K32: 46173 | L32: 46173 | M32: 10755996551 | Q32: ARREGLO DE CARGA | AH32: =M32 -> 10755996551 | AI32: =IFERROR(INDEX(PROVEEDORES!$B$1:$B$6940,MATCH(AH32,PROVEEDORES!$A$1:$A$6940,0)),"") -> PEREZ DAHUA FRANS DENNIS
A33: 15 | B33: 02 | C33: 46174 | D33: 6314 | E33: 40 | G33: S | H33: 3.417 | I33: 03 | J33: 0001-043546 | K33: 46162 | L33: 46162 | M33: 10446876312 | Q33: CONSUMO | AH33: =M33 -> 10446876312 | AI33: =IFERROR(INDEX(PROVEEDORES!$B$1:$B$6940,MATCH(AH33,PROVEEDORES!$A$1:$A$6940,0)),"") -> IRENE ELENITH ROJAS RUIZ
A34: 15 | B34: 02 | C34: 46174 | D34: 6314 | E34: 40 | G34: S | H34: 3.417 | I34: 03 | J34: 0001-043551 | K34: 46163 | L34: 46163 | M34: 10446876312 | Q34: CONSUMO | AH34: =M34 -> 10446876312 | AI34: =IFERROR(INDEX(PROVEEDORES!$B$1:$B$6940,MATCH(AH34,PROVEEDORES!$A$1:$A$6940,0)),"") -> IRENE ELENITH ROJAS RUIZ
... A45: 15 | B45: 02 | C45: 46174 | D45: 6314 | E45: 40 | G45: S | H45: 3.417 | I45: 03 | J45: 0001-043598 | K45: 46174 | L45: 46174 | M45: 10446876312 | Q45: CONSUMO | AH45: =M45 -> 10446876312 | AI45: =IFERROR(INDEX(PROVEEDORES!$B$1:$B$6940,MATCH(AH45,PROVEEDORES!$A$1:$A$6940,0)),"") -> IRENE ELENITH ROJAS RUIZ
A46: 15 | B46: 03 | C46: 46174 | D46: 14132 | F46: 650 | G46: S | H46: 3.417 | I46: PL | J46: 3613 | K46: 46164 | L46: 46164 | M46: 40018877 | Q46: RENGIFO/PUCALLPA-BAGUA-PUCALLPA/C8P765/EXCESO (0) | AH46: =M46 -> 40018877 | AI46: =IFERROR(INDEX(PROVEEDORES!$B$1:$B$6940,MATCH(AH46,PROVEEDORES!$A$1:$A$6940,0)),"") -> RENGIFO IGLESIAS HEBER
A47: 15 | B47: 03 | C47: 46174 | D47: 14132 | F47: 80 | G47: S | H47: 3.417 | I47: PL | J47: 3668 | K47: 46172 | L47: 46172 | M47: 40018877 | Q47: POR LIQUIDAR | AH47: =M47 -> 40018877 | AI47: =IFERROR(INDEX(PROVEEDORES!$B$1:$B$6940,MATCH(AH47,PROVEEDORES!$A$1:$A$6940,0)),"") -> RENGIFO IGLESIAS HEBER
A48: 15 | B48: 03 | C48: 46174 | D48: 14132 | F48: 234 | G48: S | H48: 3.417 | I48: PL | J48: 3687 | K48: 46174 | L48: 46174 | M48: 40018877 | Q48: POR LIQUIDAR | AH48: =M48 -> 40018877 | AI48: =IFERROR(INDEX(PROVEEDORES!$B$1:$B$6940,MATCH(AH48,PROVEEDORES!$A$1:$A$6940,0)),"") -> RENGIFO IGLESIAS HEBER
A49: 15 | B49: 03 | C49: 46174 | D49: 42121 | E49: 52.2 | G49: S | H49: 3.417 | I49: 01 | J49: FF01-794054 | K49: 46171 | L49: 46171 | M49: 20511004251 | Q49: PEAJE | AH49: =M49 -> 20511004251 | AI49: =IFERROR(INDEX(PROVEEDORES!$B$1:$B$6940,MATCH(AH49,PROVEEDORES!$A$1:$A$6940,0)),"") -> CONCESIONARIA IIRSA NORTE S.A.
A50: 15 | B50: 03 | C50: 46174 | D50: 42121 | E50: 52.2 | G50: S | H50: 3.417 | I50: 01 | J50: FH02-599380 | K50: 46172 | L50: 46172 | M50: 20511004251 | Q50: PEAJE | AH50: =M50 -> 20511004251 | AI50: =IFERROR(INDEX(PROVEEDORES!$B$1:$B$6940,MATCH(AH50,PROVEEDORES!$A$1:$A$6940,0)),"") -> CONCESIONARIA IIRSA NORTE S.A.
A51: 15 | B51: 03 | C51: 46174 | D51: 42121 | E51: 52.2 | G51: S | H51: 3.417 | I51: 01 | J51: FG02-684489 | K51: 46171 | L51: 46171 | M51: 20511004251 | Q51: PEAJE | AH51: =M51 -> 20511004251 | AI51: =IFERROR(INDEX(PROVEEDORES!$B$1:$B$6940,MATCH(AH51,PROVEEDORES!$A$1:$A$6940,0)),"") -> CONCESIONARIA IIRSA NORTE S.A.
A52: 15 | B52: 03 | C52: 46174 | D52: 42121 | E52: 52.2 | G52: S | H52: 3.417 | I52: 01 | J52: FG01-671032 | K52: 46170 | L52: 46170 | M52: 20511004251 | Q52: PEAJE | AH52: =M52 -> 20511004251 | AI52: =IFERROR(INDEX(PROVEEDORES!$B$1:$B$6940,MATCH(AH52,PROVEEDORES!$A$1:$A$6940,0)),"") -> CONCESIONARIA IIRSA NORTE S.A.
A53: 15 | B53: 03 | C53: 46174 | D53: 42121 | E53: 52.2 | G53: S | H53: 3.417 | I53: 01 | J53: FH01-511327 | K53: 46167 | L53: 46167 | M53: 20511004251 | Q53: PEAJE | AH53: =M53 -> 20511004251 | AI53: =IFERROR(INDEX(PROVEEDORES!$B$1:$B$6940,MATCH(AH53,PROVEEDORES!$A$1:$A$6940,0)),"") -> CONCESIONARIA IIRSA NORTE S.A.
A54: 15 | B54: 03 | C54: 46174 | D54: 42121 | E54: 30 | G54: S | H54: 3.417 | I54: 01 | J54: E001-714 | K54: 46170 | L54: 46170 | M54: 10166713442 | Q54: ALOJAMIENTO | AH54: =M54 -> 10166713442 | AI54: =IFERROR(INDEX(PROVEEDORES!$B$1:$B$6940,MATCH(AH54,PROVEEDORES!$A$1:$A$6940,0)),"") -> LEYVA CUBAS MANUEL
A55: 15 | B55: 03 | C55: 46174 | D55: 42121 | E55: 45 | G55: S | H55: 3.417 | I55: 01 | J55: E001-524 | K55: 46174 | L55: 46174 | M55: 20613201760 | Q55: SILICONA | AH55: =M55 -> 20613201760 | AI55: =IFERROR(INDEX(PROVEEDORES!$B$1:$B$6940,MATCH(AH55,PROVEEDORES!$A$1:$A$6940,0)),"") -> AUTOPARTS DAYLEN EIRL
A56: 15 | B56: 03 | C56: 46174 | D56: 42121 | E56: 40 | G56: S | H56: 3.417 | I56: 01 | J56: E001-29 | K56: 46174 | L56: 46174 | M56: 10000099495 | Q56: LAVADO | AH56: =M56 -> 10000099495 | AI56: =IFERROR(INDEX(PROVEEDORES!$B$1:$B$6940,MATCH(AH56,PROVEEDORES!$A$1:$A$6940,0)),"") -> RUIZ DE AGUILAR LUZ ELINA
A57: 15 | B57: 03 | C57: 46174 | D57: 42121 | E57: 48 | G57: S | H57: 3.417 | I57: 01 | J57: E001-33 | K57: 46174 | L57: 46174 | M57: 10000099495 | Q57: ARREGLO DE CARGA | AH57: =M57 -> 10000099495 | AI57: =IFERROR(INDEX(PROVEEDORES!$B$1:$B$6940,MATCH(AH57,PROVEEDORES!$A$1:$A$6940,0)),"") -> RUIZ DE AGUILAR LUZ ELINA
A58: 15 | B58: 03 | C58: 46174 | D58: 63433 | E58: 60 | G58: S | H58: 3.417 | I58: 03 | J58: 0001-000395 | K58: 46171 | L58: 46171 | M58: 10773806387 | Q58: REPARACION DE LLANTA | AH58: =M58 -> 10773806387 | AI58: =IFERROR(INDEX(PROVEEDORES!$B$1:$B$6940,MATCH(AH58,PROVEEDORES!$A$1:$A$6940,0)),"") -> GOMEZ ISIDRO SALY
A59: 15 | B59: 03 | C59: 46174 | D59: 6314 | E59: 40 | G59: S | H59: 3.417 | I59: 03 | J59: 001-002585 | K59: 46163 | L59: 46163 | M59: 10733685790 | Q59: CONSUMO | AH59: =M59 -> 10733685790 | AI59: =IFERROR(INDEX(PROVEEDORES!$B$1:$B$6940,MATCH(AH59,PROVEEDORES!$A$1:$A$6940,0)),"") -> ISUIZA SABINO HALBER WAGNER
A60: 15 | B60: 03 | C60: 46174 | D60: 6314 | E60: 40 | G60: S | H60: 3.417 | I60: 03 | J60: 001-002589 | K60: 46164 | L60: 46164 | M60: 10733685790 | Q60: CONSUMO | AH60: =M60 -> 10733685790 | AI60: =IFERROR(INDEX(PROVEEDORES!$B$1:$B$6940,MATCH(AH60,PROVEEDORES!$A$1:$A$6940,0)),"") -> ISUIZA SABINO HALBER WAGNER
A61: 15 | B61: 03 | C61: 46174 | D61: 6314 | E61: 40 | G61: S | H61: 3.417 | I61: 03 | J61: 0003-000517 | K61: 46165 | L61: 46165 | M61: 10804598184 | Q61: CONSUMO | AH61: =M61 -> 10804598184 | AI61: =IFERROR(INDEX(PROVEEDORES!$B$1:$B$6940,MATCH(AH61,PROVEEDORES!$A$1:$A$6940,0)),"") -> RODRIGUEZ SAAVEDRA VICTORIA
A62: 15 | B62: 03 | C62: 46174 | D62: 6314 | E62: 40 | G62: S | H62: 3.417 | I62: 03 | J62: 0003-000506 | K62: 46166 | L62: 46166 | M62: 10804598184 | Q62: CONSUMO | AH62: =M62 -> 10804598184 | AI62: =IFERROR(INDEX(PROVEEDORES!$B$1:$B$6940,MATCH(AH62,PROVEEDORES!$A$1:$A$6940,0)),"") -> RODRIGUEZ SAAVEDRA VICTORIA
A63: 15 | B63: 03 | C63: 46174 | D63: 6314 | E63: 40 | G63: S | H63: 3.417 | I63: 03 | J63: 0001-0004603 | K63: 46167 | L63: 46167 | M63: 10718880063 | Q63: CONSUMO | AH63: =M63 -> 10718880063 | AI63: =IFERROR(INDEX(PROVEEDORES!$B$1:$B$6940,MATCH(AH63,PROVEEDORES!$A$1:$A$6940,0)),"") -> DIAZ VILLALOBOS DIMAS
A64: 15 | B64: 03 | C64: 46174 | D64: 6314 | E64: 40 | G64: S | H64: 3.417 | I64: 03 | J64: 0001-0004612 | K64: 46168 | L64: 46168 | M64: 10718880063 | Q64: CONSUMO | AH64: =M64 -> 10718880063 | AI64: =IFERROR(INDEX(PROVEEDORES!$B$1:$B$6940,MATCH(AH64,PROVEEDORES!$A$1:$A$6940,0)),"") -> DIAZ VILLALOBOS DIMAS
A65: 15 | B65: 03 | C65: 46174 | D65: 6314 | E65: 40 | G65: S | H65: 3.417 | I65: 03 | J65: 0001-0004613 | K65: 46169 | L65: 46169 | M65: 10718880063 | Q65: CONSUMO | AH65: =M65 -> 10718880063 | AI65: =IFERROR(INDEX(PROVEEDORES!$B$1:$B$6940,MATCH(AH65,PROVEEDORES!$A$1:$A$6940,0)),"") -> DIAZ VILLALOBOS DIMAS
A66: 15 | B66: 03 | C66: 46174 | D66: 6314 | E66: 40 | G66: S | H66: 3.417 | I66: 03 | J66: 0001-009027 | K66: 46170 | L66: 46170 | M66: 10011445522 | Q66: CONSUMO | AH66: =M66 -> 10011445522 | AI66: =IFERROR(INDEX(PROVEEDORES!$B$1:$B$6940,MATCH(AH66,PROVEEDORES!$A$1:$A$6940,0)),"") -> LLENI SHUÑA CORDOVA
A67: 15 | B67: 03 | C67: 46174 | D67: 42121 | E67: 40 | G67: S | H67: 3.417 | I67: 01 | J67: E001-4912 | K67: 46171 | L67: 46171 | M67: 10749424392 | Q67: CONSUMO | AH67: =M67 -> 10749424392 | AI67: =IFERROR(INDEX(PROVEEDORES!$B$1:$B$6940,MATCH(AH67,PROVEEDORES!$A$1:$A$6940,0)),"") -> COJAL MEDINA ANA ELIZABETH
A68: 15 | B68: 03 | C68: 46174 | D68: 6314 | E68: 40 | G68: S | H68: 3.417 | I68: 03 | J68: 0001-026271 | K68: 46172 | L68: 46172 | M68: 10805861342 | Q68: CONSUMO | AH68: =M68 -> 10805861342 | AI68: =IFERROR(INDEX(PROVEEDORES!$B$1:$B$6940,MATCH(AH68,PROVEEDORES!$A$1:$A$6940,0)),"") -> CASTILLO QUISPE ALBERTO
A69: 15 | B69: 03 | C69: 46174 | D69: 6314 | E69: 40 | G69: S | H69: 3.417 | I69: 03 | J69: 0001-0000666 | K69: 46173 | L69: 46173 | M69: 10453880732 | Q69: CONSUMO | AH69: =M69 -> 10453880732 | AI69: =IFERROR(INDEX(PROVEEDORES!$B$1:$B$6940,MATCH(AH69,PROVEEDORES!$A$1:$A$6940,0)),"") -> DE LA BARRA PAREDES MARIA ROSA
A70: 15 | B70: 03 | C70: 46174 | D70: 42121 | E70: 40 | G70: S | H70: 3.417 | I70: 01 | J70: E001-681 | K70: 46174 | L70: 46174 | M70: 10752722701 | Q70: CONSUMO | AH70: =M70 -> 10752722701 | AI70: =IFERROR(INDEX(PROVEEDORES!$B$1:$B$6940,MATCH(AH70,PROVEEDORES!$A$1:$A$6940,0)),"") -> GONGORA GUERRA DARA BRIGITH
A71: 15 | B71: 04 | C71: 46174 | D71: 14132 | F71: 650 | G71: S | H71: 3.417 | I71: PL | J71: 3625 | K71: 46167 | L71: 46167 | M71: 17550145 | Q71: MIÑAN/PUCALLPA-YURIMAGUAS-PUCALLPA/F5Q882/EXCESO (0) | AH71: =M71 -> 17550145 | AI71: =IFERROR(INDEX(PROVEEDORES!$B$1:$B$6940,MATCH(AH71,PROVEEDORES!$A$1:$A$6940,0)),"") -> MIÑAN ODAR JOSE MIGUEL
A72: 15 | B72: 04 | C72: 46174 | D72: 14132 | F72: 66.2 | G72: S | H72: 3.417 | I72: PL | J72: 3689 | K72: 46174 | L72: 46174 | M72: 17550145 | Q72: POR LIQUIDAR | AH72: =M72 -> 17550145 | AI72: =IFERROR(INDEX(PROVEEDORES!$B$1:$B$6940,MATCH(AH72,PROVEEDORES!$A$1:$A$6940,0)),"") -> MIÑAN ODAR JOSE MIGUEL
A73: 15 | B73: 04 | C73: 46174 | D73: 42121 | E73: 52.2 | G73: S | H73: 3.417 | I73: 01 | J73: FI02-764307 | K73: 46172 | L73: 46172 | M73: 20511004251 | Q73: PEAJE | AH73: =M73 -> 20511004251 | AI73: =IFERROR(INDEX(PROVEEDORES!$B$1:$B$6940,MATCH(AH73,PROVEEDORES!$A$1:$A$6940,0)),"") -> CONCESIONARIA IIRSA NORTE S.A.
A74: 15 | B74: 04 | C74: 46174 | D74: 42121 | E74: 52.2 | G74: S | H74: 3.417 | I74: 01 | J74: FI01-752232 | K74: 46172 | L74: 46172 | M74: 20511004251 | Q74: PEAJE | AH74: =M74 -> 20511004251 | AI74: =IFERROR(INDEX(PROVEEDORES!$B$1:$B$6940,MATCH(AH74,PROVEEDORES!$A$1:$A$6940,0)),"") -> CONCESIONARIA IIRSA NORTE S.A.
A75: 15 | B75: 04 | C75: 46174 | D75: 42121 | E75: 70 | G75: S | H75: 3.417 | I75: 01 | J75: F001-1849 | K75: 46172 | L75: 46172 | M75: 20177662446 | Q75: INGRESO A PUERTO | AH75: =M75 -> 20177662446 | AI75: =IFERROR(INDEX(PROVEEDORES!$B$1:$B$6940,MATCH(AH75,PROVEEDORES!$A$1:$A$6940,0)),"") -> MUNICIPALIDAD PROVINCIAL DE ALTO AMAZONAS
A76: 15 | B76: 04 | C76: 46174 | D76: 42121 | E76: 138.8 | G76: S | H76: 3.417 | I76: 01 | J76: F019-26438 | K76: 46172 | L76: 46172 | M76: 20100003199 | Q76: ENAPU | AH76: =M76 -> 20100003199 | AI76: =IFERROR(INDEX(PROVEEDORES!$B$1:$B$6940,MATCH(AH76,PROVEEDORES!$A$1:$A$6940,0)),"") -> EMP NACIONAL DE PUERTOS S A
A77: 15 | B77: 04 | C77: 46174 | D77: 42121 | E77: 40 | G77: S | H77: 3.417 | I77: 01 | J77: FF01-4612 | K77: 46174 | L77: 46174 | M77: 10755996551 | Q77: LAVADO | AH77: =M77 -> 10755996551 | AI77: =IFERROR(INDEX(PROVEEDORES!$B$1:$B$6940,MATCH(AH77,PROVEEDORES!$A$1:$A$6940,0)),"") -> PEREZ DAHUA FRANS DENNIS
A78: 15 | B78: 04 | C78: 46174 | D78: 42121 | E78: 43 | G78: S | H78: 3.417 | I78: 01 | J78: FF01-4613 | K78: 46174 | L78: 46174 | M78: 10755996551 | Q78: ARREGLO DE CARGA | AH78: =M78 -> 10755996551 | AI78: =IFERROR(INDEX(PROVEEDORES!$B$1:$B$6940,MATCH(AH78,PROVEEDORES!$A$1:$A$6940,0)),"") -> PEREZ DAHUA FRANS DENNIS
A79: 15 | B79: 04 | C79: 46174 | D79: 6314 | E79: 40 | G79: S | H79: 3.417 | I79: 03 | J79: 0001-011619 | K79: 46167 | L79: 46167 | M79: 10481118048 | Q79: CONSUMO | AH79: =M79 -> 10481118048 | AI79: =IFERROR(INDEX(PROVEEDORES!$B$1:$B$6940,MATCH(AH79,PROVEEDORES!$A$1:$A$6940,0)),"") -> RIOS DAVILA INGRID JOHANNA
A80: 15 | B80: 04 | C80: 46174 | D80: 6314 | E80: 40 | G80: S | H80: 3.417 | I80: 03 | J80: 0001-015000 | K80: 46168 | L80: 46168 | M80: 10230126807 | Q80: CONSUMO | AH80: =M80 -> 10230126807 | AI80: =IFERROR(INDEX(PROVEEDORES!$B$1:$B$6940,MATCH(AH80,PROVEEDORES!$A$1:$A$6940,0)),"") -> SANTAMARIA PUCLLA ANDRES
A81: 15 | B81: 04 | C81: 46174 | D81: 6314 | E81: 40 | G81: S | H81: 3.417 | I81: 03 | J81: 0001-004209 | K81: 46169 | L81: 46169 | M81: 10414823080 | Q81: CONSUMO | AH81: =M81 -> 10414823080 | AI81: =IFERROR(INDEX(PROVEEDORES!$B$1:$B$6940,MATCH(AH81,PROVEEDORES!$A$1:$A$6940,0)),"") -> TOLENTINO SIMON REINA
A82: 15 | B82: 04 | C82: 46174 | D82: 42121 | E82: 40 | G82: S | H82: 3.417 | I82: 01 | J82: E001-5134 | K82: 46170 | L82: 46170 | M82: 10460826930 | Q82: CONSUMO | AH82: =M82 -> 10460826930 | AI82: =IFERROR(INDEX(PROVEEDORES!$B$1:$B$6940,MATCH(AH82,PROVEEDORES!$A$1:$A$6940,0)),"") -> MONDRAGON REQUEJO LUZ NEYDA
A83: 15 | B83: 04 | C83: 46174 | D83: 6314 | E83: 40 | G83: S | H83: 3.417 | I83: 03 | J83: 003-000155 | K83: 46171 | L83: 46171 | M83: 10011096056 | Q83: CONSUMO | AH83: =M83 -> 10011096056 | AI83: =IFERROR(INDEX(PROVEEDORES!$B$1:$B$6940,MATCH(AH83,PROVEEDORES!$A$1:$A$6940,0)),"") -> BACA NUÑEZ JAIME RAFAEL
A84: 15 | B84: 04 | C84: 46174 | D84: 42121 | E84: 40 | G84: S | H84: 3.417 | I84: 01 | J84: E001-1658 | K84: 46172 | L84: 46172 | M84: 10407638714 | Q84: CONSUMO | AH84: =M84 -> 10407638714 | AI84: =IFERROR(INDEX(PROVEEDORES!$B$1:$B$6940,MATCH(AH84,PROVEEDORES!$A$1:$A$6940,0)),"") -> ROMERO MURRIETA ELIZABETH
... A86: 15 | B86: 04 | C86: 46174 | D86: 6314 | E86: 40 | G86: S | H86: 3.417 | I86: 03 | J86: 001-002558 | K86: 46174 | L86: 46174 | M86: 10733685790 | Q86: CONSUMO | AH86: =M86 -> 10733685790 | AI86: =IFERROR(INDEX(PROVEEDORES!$B$1:$B$6940,MATCH(AH86,PROVEEDORES!$A$1:$A$6940,0)),"") -> ISUIZA SABINO HALBER WAGNER
A87: 15 | B87: 05 | C87: 46174 | D87: 14132 | F87: 300 | G87: S | H87: 3.417 | I87: PL | J87: 3652 | K87: 46171 | L87: 46171 | M87: 45270106 | Q87: VILLAR/PUCALLPA-SAN ALEJANDRO-PUCALLPA/ALX944/EXCESO (0) | AH87: =M87 -> 45270106 | AI87: =IFERROR(INDEX(PROVEEDORES!$B$1:$B$6940,MATCH(AH87,PROVEEDORES!$A$1:$A$6940,0)),"") -> VILLAR ARMAS CARLOS DAVID
A88: 15 | B88: 05 | C88: 46174 | D88: 42121 | E88: 45 | G88: S | H88: 3.417 | I88: 01 | J88: FF01-4580 | K88: 46172 | L88: 46172 | M88: 10755996551 | Q88: ARTICULOS DE LIMPIEZA | AH88: =M88 -> 10755996551 | AI88: =IFERROR(INDEX(PROVEEDORES!$B$1:$B$6940,MATCH(AH88,PROVEEDORES!$A$1:$A$6940,0)),"") -> PEREZ DAHUA FRANS DENNIS
A89: 15 | B89: 05 | C89: 46174 | D89: 42121 | E89: 55 | G89: S | H89: 3.417 | I89: 01 | J89: FF01-4618 | K89: 46174 | L89: 46174 | M89: 10755996551 | Q89: ENGRASE | AH89: =M89 -> 10755996551 | AI89: =IFERROR(INDEX(PROVEEDORES!$B$1:$B$6940,MATCH(AH89,PROVEEDORES!$A$1:$A$6940,0)),"") -> PEREZ DAHUA FRANS DENNIS
A90: 15 | B90: 05 | C90: 46174 | D90: 6314 | E90: 40 | G90: S | H90: 3.417 | I90: 03 | J90: 0001-043602 | K90: 46167 | L90: 46167 | M90: 10446876312 | Q90: CONSUMO | AH90: =M90 -> 10446876312 | AI90: =IFERROR(INDEX(PROVEEDORES!$B$1:$B$6940,MATCH(AH90,PROVEEDORES!$A$1:$A$6940,0)),"") -> IRENE ELENITH ROJAS RUIZ
A91: 15 | B91: 05 | C91: 46174 | D91: 6314 | E91: 40 | G91: S | H91: 3.417 | I91: 03 | J91: 0002-003376 | K91: 46170 | L91: 46170 | M91: 10803878817 | Q91: CONSUMO | AH91: =M91 -> 10803878817 | AI91: =IFERROR(INDEX(PROVEEDORES!$B$1:$B$6940,MATCH(AH91,PROVEEDORES!$A$1:$A$6940,0)),"") -> BETETA DIMAS LUCY LUZMILA
A92: 15 | B92: 05 | C92: 46174 | D92: 6314 | E92: 40 | G92: S | H92: 3.417 | I92: 03 | J92: 0002-003378 | K92: 46171 | L92: 46171 | M92: 10803878817 | Q92: CONSUMO | AH92: =M92 -> 10803878817 | AI92: =IFERROR(INDEX(PROVEEDORES!$B$1:$B$6940,MATCH(AH92,PROVEEDORES!$A$1:$A$6940,0)),"") -> BETETA DIMAS LUCY LUZMILA
A93: 15 | B93: 05 | C93: 46174 | D93: 42121 | E93: 40 | G93: S | H93: 3.417 | I93: 01 | J93: E001-40 | K93: 46172 | L93: 46172 | M93: 10001739633 | Q93: CONSUMO | AH93: =M93 -> 10001739633 | AI93: =IFERROR(INDEX(PROVEEDORES!$B$1:$B$6940,MATCH(AH93,PROVEEDORES!$A$1:$A$6940,0)),"") -> HERNANDEZ LOZANO CARLOS EDUARDO
A94: 15 | B94: 05 | C94: 46174 | D94: 6314 | E94: 40 | G94: S | H94: 3.417 | I94: 03 | J94: 0001-043604 | K94: 46174 | L94: 46174 | M94: 10446876312 | Q94: CONSUMO | AH94: =M94 -> 10446876312 | AI94: =IFERROR(INDEX(PROVEEDORES!$B$1:$B$6940,MATCH(AH94,PROVEEDORES!$A$1:$A$6940,0)),"") -> IRENE ELENITH ROJAS RUIZ
A95: 15 | B95: 06 | C95: 46175 | D95: 14132 | F95: 750 | G95: S | H95: 3.424 | I95: PL | J95: 3601 | K95: 46163 | L95: 46163 | M95: 40980389 | Q95: APAZA/PUCALLPA-JAEN-PUCALLPA/C3G749/EXCESO (0) | AH95: =M95 -> 40980389 | AI95: =IFERROR(INDEX(PROVEEDORES!$B$1:$B$6940,MATCH(AH95,PROVEEDORES!$A$1:$A$6940,0)),"") -> APAZA HUMPIRI VICTOR EDGAR
A96: 15 | B96: 06 | C96: 46175 | D96: 14132 | F96: 266.2 | G96: S | H96: 3.424 | I96: PL | J96: 3706 | K96: 46175 | L96: 46175 | M96: 40980389 | Q96: POR LIQUIDAR | AH96: =M96 -> 40980389 | AI96: =IFERROR(INDEX(PROVEEDORES!$B$1:$B$6940,MATCH(AH96,PROVEEDORES!$A$1:$A$6940,0)),"") -> APAZA HUMPIRI VICTOR EDGAR
A97: 15 | B97: 06 | C97: 46175 | D97: 42121 | E97: 52.2 | G97: S | H97: 3.424 | I97: 01 | J97: FF01-793467 | K97: 46167 | L97: 46167 | M97: 20511004251 | Q97: PEAJE | AH97: =M97 -> 20511004251 | AI97: =IFERROR(INDEX(PROVEEDORES!$B$1:$B$6940,MATCH(AH97,PROVEEDORES!$A$1:$A$6940,0)),"") -> CONCESIONARIA IIRSA NORTE S.A.
A98: 15 | B98: 06 | C98: 46175 | D98: 42121 | E98: 52.2 | G98: S | H98: 3.424 | I98: 01 | J98: FE01-1273249 | K98: 46167 | L98: 46167 | M98: 20511004251 | Q98: PEAJE | AH98: =M98 -> 20511004251 | AI98: =IFERROR(INDEX(PROVEEDORES!$B$1:$B$6940,MATCH(AH98,PROVEEDORES!$A$1:$A$6940,0)),"") -> CONCESIONARIA IIRSA NORTE S.A.
A99: 15 | B99: 06 | C99: 46175 | D99: 42121 | E99: 52.2 | G99: S | H99: 3.424 | I99: 01 | J99: FH02-599370 | K99: 46172 | L99: 46172 | M99: 20511004251 | Q99: PEAJE | AH99: =M99 -> 20511004251 | AI99: =IFERROR(INDEX(PROVEEDORES!$B$1:$B$6940,MATCH(AH99,PROVEEDORES!$A$1:$A$6940,0)),"") -> CONCESIONARIA IIRSA NORTE S.A.
A100: 15 | B100: 06 | C100: 46175 | D100: 42121 | E100: 52.2 | G100: S | H100: 3.424 | I100: 01 | J100: FG01-670575 | K100: 46197 | L100: 46197 | M100: 20511004251 | Q100: PEAJE | AH100: =M100 -> 20511004251 | AI100: =IFERROR(INDEX(PROVEEDORES!$B$1:$B$6940,MATCH(AH100,PROVEEDORES!$A$1:$A$6940,0)),"") -> CONCESIONARIA IIRSA NORTE S.A.
A101: 15 | B101: 06 | C101: 46175 | D101: 42121 | E101: 52.2 | G101: S | H101: 3.424 | I101: 01 | J101: FG02-684193 | K101: 46169 | L101: 46169 | M101: 20511004251 | Q101: PEAJE | AH101: =M101 -> 20511004251 | AI101: =IFERROR(INDEX(PROVEEDORES!$B$1:$B$6940,MATCH(AH101,PROVEEDORES!$A$1:$A$6940,0)),"") -> CONCESIONARIA IIRSA NORTE S.A.
A102: 15 | B102: 06 | C102: 46175 | D102: 42121 | E102: 52.2 | G102: S | H102: 3.424 | I102: 01 | J102: FH01-511113 | K102: 46166 | L102: 46166 | M102: 20511004251 | Q102: ALOJAMIENTO | AH102: =M102 -> 20511004251 | AI102: =IFERROR(INDEX(PROVEEDORES!$B$1:$B$6940,MATCH(AH102,PROVEEDORES!$A$1:$A$6940,0)),"") -> CONCESIONARIA IIRSA NORTE S.A.
A103: 15 | B103: 06 | C103: 46175 | D103: 42121 | E103: 40 | G103: S | H103: 3.424 | I103: 01 | J103: E001-7305 | K103: 46168 | L103: 46168 | M103: 20610821775 | Q103: COCHERA | AH103: =M103 -> 20610821775 | AI103: =IFERROR(INDEX(PROVEEDORES!$B$1:$B$6940,MATCH(AH103,PROVEEDORES!$A$1:$A$6940,0)),"") -> KM 16 FOOD & PARKING E.I.R.L.
A104: 15 | B104: 06 | C104: 46175 | D104: 42121 | E104: 20 | G104: S | H104: 3.424 | I104: 01 | J104: E001-7307 | K104: 46168 | L104: 46168 | M104: 20610821775 | Q104: COCHERA | AH104: =M104 -> 20610821775 | AI104: =IFERROR(INDEX(PROVEEDORES!$B$1:$B$6940,MATCH(AH104,PROVEEDORES!$A$1:$A$6940,0)),"") -> KM 16 FOOD & PARKING E.I.R.L.
A105: 15 | B105: 06 | C105: 46175 | D105: 42121 | E105: 30 | G105: S | H105: 3.424 | I105: 01 | J105: FE04-2627 | K105: 46171 | L105: 46171 | M105: 10443039517 | Q105: ALOJAMIENTO | AH105: =M105 -> 10443039517 | AI105: =IFERROR(INDEX(PROVEEDORES!$B$1:$B$6940,MATCH(AH105,PROVEEDORES!$A$1:$A$6940,0)),"") -> BANDA OCHOA REYES
A106: 15 | B106: 06 | C106: 46175 | D106: 42121 | E106: 40 | G106: S | H106: 3.424 | I106: 01 | J106: FF01-4619 | K106: 46174 | L106: 46174 | M106: 10755996551 | Q106: LAVADO | AH106: =M106 -> 10755996551 | AI106: =IFERROR(INDEX(PROVEEDORES!$B$1:$B$6940,MATCH(AH106,PROVEEDORES!$A$1:$A$6940,0)),"") -> PEREZ DAHUA FRANS DENNIS
A107: 15 | B107: 06 | C107: 46175 | D107: 42121 | E107: 53 | G107: S | H107: 3.424 | I107: 01 | J107: FF01-4620 | K107: 46174 | L107: 46174 | M107: 10755996551 | Q107: ARREGLO DE CARGA | AH107: =M107 -> 10755996551 | AI107: =IFERROR(INDEX(PROVEEDORES!$B$1:$B$6940,MATCH(AH107,PROVEEDORES!$A$1:$A$6940,0)),"") -> PEREZ DAHUA FRANS DENNIS
A108: 15 | B108: 06 | C108: 46175 | D108: 6314 | E108: 40 | G108: S | H108: 3.424 | I108: 03 | J108: 0002-003365 | K108: 46163 | L108: 46163 | M108: 10803878817 | Q108: CONSUMO | AH108: =M108 -> 10803878817 | AI108: =IFERROR(INDEX(PROVEEDORES!$B$1:$B$6940,MATCH(AH108,PROVEEDORES!$A$1:$A$6940,0)),"") -> BETETA DIMAS LUCY LUZMILA
... A120: 15 | B120: 06 | C120: 46175 | D120: 42121 | E120: 40 | G120: S | H120: 3.424 | I120: 01 | J120: E001-407 | K120: 46175 | L120: 46175 | M120: 10205944147 | Q120: CONSUMO | AH120: =M120 -> 10205944147 | AI120: =IFERROR(INDEX(PROVEEDORES!$B$1:$B$6940,MATCH(AH120,PROVEEDORES!$A$1:$A$6940,0)),"") -> PEREZ CLEMENTE LUIS ALBERTO
A121: 15 | B121: 07 | C121: 46175 | D121: 14132 | F121: 300 | G121: S | H121: 3.424 | I121: PL | J121: 3662 | K121: 46171 | L121: 46171 | M121: 33429469 | Q121: CUEVA/PUCALLPA-JUANJUI-PUCALLPA/CLK835/EXCESO (0) | AH121: =M121 -> 33429469 | AI121: =IFERROR(INDEX(PROVEEDORES!$B$1:$B$6940,MATCH(AH121,PROVEEDORES!$A$1:$A$6940,0)),"") -> CUEVA ZUTA SEGUNDO JUAN
A122: 15 | B122: 07 | C122: 46175 | D122: 14132 | F122: 98 | G122: S | H122: 3.424 | I122: PL | J122: 3709 | K122: 46175 | L122: 46175 | M122: 33429469 | Q122: POR LIQUIDAR | AH122: =M122 -> 33429469 | AI122: =IFERROR(INDEX(PROVEEDORES!$B$1:$B$6940,MATCH(AH122,PROVEEDORES!$A$1:$A$6940,0)),"") -> CUEVA ZUTA SEGUNDO JUAN
...

Sheet DATOS
A2: EJEMPLO
A3: POR LIQUIDAR EN EL HABER | E3: 14132
A4: BV DEBE | D4: 6314
A5: FT DEBE | D5: 42121
A7: CUENTA | B7: CONCEPTO | F7: TIPO DE DOCUMENTO
A8: 14131 | B8: LIQUIDACION LIMA | F8: 01 | G8: FACTURA
A9: 14132 | B9: LIQUIDACION PUCLLPA | F9: 02 | G9: RECIBO POR HONORARIO
A10: 141321 | B10: LIQUIDACION PUCLLPA (RRHH) | F10: 03 | G10: BOLETA DE VENTA
A11: 14133 | B11: LIQUIDACION TARAPOTO | F11: RI | G11: RECIBO DE INGRESO
A12: 141331 | B12: LIQUIDACION TARAPOTO (RRHH) | F12: PL | G12: POR LIQUIDAR
A13: 6314 | B13: POR CONSUMO
A14: 6313 | B14: ALOJAMIENTO
A15: 63433 | B15: LAVADO DE UNIDAD
A16: 63433 | B16: CAMBIO DE LLANTA
A17: 63433 | B17: AJUSTE DE LLANTA
A18: 63113 | B18: PEAJE
A19: 4241 | B19: CONCEPTO QUE INDIQUE
A20: 42121 | B20: CONCEPTO QUE INDIQUE

Sheet PROVEEDORES
A1: RUC O DNI | B1: RAZON SOCIAL | C1: APELLIDO 1 | D1: APELLIDO 2 | E1: NOMBRE 1 | F1: NOMBRE 2 | G1: TIPO
A2: 20494017955 | B2: "MULTISERVICIOS CALDERON V E.I.R.L." | G2: Proveedor
A3: 10218598361 | B3: ASTORAYME ORTIZ EDWIN ERACLIO | C3: ASTORAYME | D3: ORTIZ | E3: EDWIN | F3: ERACLIO | G3: Proveedor
A4: 10011660385 | B4: CASTILLO JIMENEZ JOSE ANTONIO | C4: CASTILLO | D4: JIMENEZ | E4: JOSE | F4: ANTONIO | G4: Proveedor
A5: 10337266750 | B5: IZQUIERDO PERALTA ERMILA | C5: IZQUIERDO | D5: PERALTA | E5: ERMILA | G5: Proveedor
A6: 10475916196 | B6: LEON TARAZONA ELMER LORENZO | C6: LEON | D6: TARAZONA | E6: ELMER | F6: LORENZO | G6: Proveedor
A7: 20601765234 | B7: OJOJOI E.I.R.L | G7: Proveedor
A8: 10448823500 | B8: PEÑA JUSTANO JUAN ABEL | C8: PEÑA | D8: JUSTANO | E8: JUAN | F8: ABEL | G8: Proveedor
A9: 10224959562 | B9: RETIS FANAN BONIFACIO | C9: RETIS | D9: FANAN | E9: BONIFACIO | G9: Proveedor
A10: 10224242021 | B10: ROJAS OCAMPO ANGELICA MARGARITA | C10: ROJAS | D10: OCAMPO | E10: ANGELICA | F10: MARGARITA | G10: Proveedor
A11: 10479390687 | B11: TAFUR BOGARIN INGRIS RULI | C11: TAFUR | D11: BOGARIN | E11: INGRIS | F11: RULI | G11: Proveedor
A12: 10001644667 | B12: TELLO GONZALEZ JUSTINIANO EDWIN | C12: TELLO | D12: GONZALEZ | E12: JUSTINIANO | F12: EDWIN | G12: Proveedor
A13: 20600611347 | B13: 20600611347.00 | G13: Proveedor
A14: 20601776767 | B14: 500 GRADOS S.A.C. | G14: Proveedor
A15: 20393772337 | B15: 9 DE OCTUBRE EMPRESA DE INVERSIONES TURISTICOS E.I.R.L. | G15: Proveedor
A16: 10466119534 | B16: ABAD ALEJANDRIA MANUEL | C16: ABAD | D16: ALEJANDRIA | E16: MANUEL | G16: Proveedor
A17: 10477136341 | B17: ABANTO CARRASCAL GRETY | C17: ABANTO | D17: CARRASCAL | E17: GRETY | G17: Proveedor
A18: 10189865797 | B18: ABANTO SALAS CIRIA IRAIDA | C18: ABANTO | D18: SALAS | E18: CIRIA | F18: IRAIDA | G18: Proveedor
A19: 10436985130 | B19: ABEL RAMIREZ TANANTA | C19: ABEL | D19: RAMIREZ | E19: TANANTA | G19: Proveedor
A20: 10200301906 | B20: ABREGU ARROYO DE ALVARADO YOLANDA | C20: ABREGU | D20: ARROYO | E20: YOLANDA | G20: Proveedor
A21: 20603743611 | B21: ACCESORIOS LA SOLUCION E.I.R.L. | G21: Proveedor
A22: 20446460481 | B22: ACERO COMERCIAL S.R.L. | G22: Proveedor
A23: 20393465329 | B23: ACEROS FLOVICSA SELVA S.A.C. | G23: Proveedor
A24: 10421133218 | B24: ACEVEDO CASTILLO CARLOS EMERSON | C24: ACEVEDO | D24: CASTILLO | E24: CARLOS | F24: EMERSON | G24: Proveedor
A25: 10421881575 | B25: ACOSTA RIOS MARIA ESTHER | C25: ACOSTA | D25: RIOS | E25: MARIA | F25: ESTHER | G25: Proveedor
A26: 10277322990 | B26: ACUNA FERNANDEZ MARIA AURORA | C26: MARIA | D26: AURORA | E26: ACUNA | F26: FERNANDEZ | G26: Proveedor
A27: 10482952424 | B27: ACUÑA FRANCO AGUSTIN | C27: ACUÑA | D27: FRANCO | E27: AGUSTIN | G27: Proveedor
A28: 10010344668 | B28: ACUÑA ZAGACETA SENAIDA CONSUELO | C28: ACUÑA | D28: ZAGACETA | E28: SENAIDA | F28: CONSUELO | G28: Proveedor
A29: 10431787861 | B29: ADAMS LOPEZ JIMI JAMES | C29: JIMI | D29: JAMES | E29: ADAMS | F29: LOPEZ | G29: Proveedor
A30: 00088151 | B30: ADAN LANFRANCO VASQUEZ | C30: ADAN | E30: LANFRANCO | F30: VASQUEZ | G30: Cliente
A31: 10802538028 | B31: ADELINDA MEJIA CABRERA | C31: MEJIA | D31: CABRERA | E31: ADELINDA | G31: Proveedor
A32: 10009668581 | B32: ADELMO IRENE SEGURA | C32: ADELMO | D32: IRENE | E32: SEGURA | G32: Proveedor
A33: 10435085291 | B33: ADRIANO MURGA ELVIS WIDMAN | C33: ADRIANO | D33: MURGA | E33: ELVIS | F33: WIDMAN | G33: Proveedor
A34: 10714795827 | B34: ADRIANZEN ARIAS LUIS EDUARDO | G34: Proveedor
A35: 10278235501 | B35: ADRIANZEN SOLANO ROSA ELVIRA | C35: ADRIANZEN | D35: SOLANO | E35: ROSA | F35: ELVIRA | G35: Proveedor
A36: 10405863591 | B36: ADRIANZEN VELASCO JULIO CESAR | C36: ADRIANZEN | D36: VELASCO | E36: JULIO | F36: CESAR | G36: Proveedor
A37: 20604013551 | B37: ADRIKA REVISIONES VEHICULARES SOCIEDAD ANÓNIMA CERRADA | G37: Proveedor
A38: 20568832664 | B38: AGRO FERRETERIA GAVINO S.A.C. | G38: Proveedor
A39: 20393686171 | B39: AGROINDUSTRIAS G. SHULLER E.I.R.L. | G39: Proveedor
A40: 20480650825 | B40: AGRONEGOCIOS & CIA S.A.C. | G40: Proveedor
A41: 10445107901 | B41: AGÜERO NIETO MARTHA | C41: AGÜERO | D41: NIETO | E41: MARTHA | G41: Proveedor
A42: 10224985253 | B42: AGUILAR LEON REMY | C42: AGUILAR | D42: LEON | E42: REMY | G42: Proveedor
A43: 10420248496 | B43: AGUILAR LEON YERTA NOEMI | C43: AGUILAR | D43: LEON | E43: YERTA | F43: NOEMI | G43: Proveedor
A44: 10455921819 | B44: AGUILAR MANSILLA LUIS ALBERTO | G44: Proveedor
A45: 10441090426 | B45: AGUILAR MONDRAGON KLINFOR | C45: AGUILAR | D45: MONDRAGON | E45: KLINFOR | G45: Proveedor
A46: 10178761957 | B46: AGUILAR QUEZADA CELSO VICTOR | C46: CELSO | D46: VICTOR | E46: AGUILAR | F46: QUEZADA | G46: Proveedor
A47: 10433356077 | B47: AGUILAR REYES NILDA | C47: NILDA | E47: AGUILAR | F47: REYES | G47: Proveedor
A48: 10428916293 | B48: AGUILAR SABOYA ELVIS | C48: ELVIS | E48: AGUILAR | F48: SABOYA | G48: Proveedor
A49: 10009931096 | B49: AGUILAR TELLO JUANA TEODOCIA | C49: AGUILAR | D49: TELLO | E49: JUANA | F49: TEODOCIA | G49: Proveedor
A50: 10438672538 | B50: AGUIRRE CRISOSTOMO ELSA VIOLETA | C50: AGUIRRE | D50: CRISOSTOMO | E50: ELSA | F50: VIOLETA | G50: Proveedor
A51: 10435525089 | B51: AGUIRRE GUTIERREZ GIOVANI | C51: AGUIRRE | D51: GUTIERREZ | E51: GIOVANI | G51: Proveedor
A52: 10414521563 | B52: AGUIRRE MALQUI ASIRIA NAFIS | C52: AGUIRRE | D52: MALQUI | E52: ASIRIA | F52: NAFIS | G52: Proveedor
A53: 44257006 | B53: AGUIRRE REATEGUI MARDEN JUNIOR | C53: MARDEN | D53: JUNIOR | E53: AGUIRRE | F53: REATEGUI | G53: Empleados
A54: 10040607043 | B54: AGUIRRE RUBIN RAFAELA | C54: AGUIRRE | D54: RUBIN | E54: RAFAELA | G54: Proveedor
A55: 10001829683 | B55: AIDE COSAR SOLORZANO | C55: AIDE | D55: COSAR | E55: SOLORZANO | G55: Proveedor
A56: 10236435712 | B56: AIDEE CLAUDIA SEDANO TORRES | C56: AIDEE | D56: CLAUDIA | E56: SEDANO | F56: TORRES | G56: Proveedor
A57: 10001819742 | B57: AJILIO FLORES SILVA | C57: AJILIO | D57: FLORES | E57: SILVA | G57: Proveedor
A58: 10432002573 | B58: ALANIA SOTO CONNIE BRISAIDA | C58: ALANIA | D58: SOTO | E58: CONNIE | F58: BRISAIDA | G58: Proveedor
A59: 10446393222 | B59: ALARCON CARRANZA NELLY YOLANDA | C59: ALARCON | D59: CARRANZA | E59: NELLY | F59: YOLANDA | G59: Proveedor
A60: 10405390685 | B60: ALARCON FERNANDEZ SARA | C60: ALARCON | D60: FERNANDEZ | E60: SARA | G60: Proveedor
A61: 10736869956 | B61: ALARCON PEREZ RITH EBERTH YERCI | C61: ALARCON | D61: PEREZ | E61: RITH | F61: EBERTH | G61: Proveedor
A62: 10403613997 | B62: ALARCON TELLO ORFELINA | C62: ALARCON | D62: TELLO | E62: ORFELINA | G62: Proveedor
A63: 10336753665 | B63: ALARCON TORO LUCINDA | C63: ALARCON | D63: TORO | E63: LUCINDA | G63: Proveedor
A64: 20609197006 | B64: ALAYO & HIJOS S.A.C. | G64: Proveedor
A65: 10434359347 | B65: ALAYO PAREDES NORLITH | C65: NORLITH | E65: ALAYO | F65: PAREDES | G65: Proveedor
A66: 10403306806 | B66: ALBA LUCIA GARATE TRIGOSO | C66: GARATE | D66: TRIGOSO | E66: ALBA | F66: LUCIA | G66: Proveedor
A67: 10421298683 | B67: ALBARADO AVELINO CONCEPCION | C67: ALBARADO | D67: AVELINO | E67: CONCEPCION | G67: Proveedor
A68: 10433507814 | B68: ALBERCA ALBERCA GEYSER TEODOMIRO | C68: ALBERCA | D68: ALBERCA | E68: GEYSER | F68: TEODOMIRO | G68: Proveedor
A69: 10208919526 | B69: ALBERTO TAPIA JAIME EDWIN | C69: ALBERTO | D69: TAPIA | E69: JAIME | F69: EDWIN | G69: Proveedor
A70: 09927823 | B70: ALCOCER VERIZUETA RONALD ALEX | G70: Terceros
A71: 10231706912 | B71: ALCOSER HUYATA TERESA MARLENY | C71: ALCOSER | D71: HUYATA | E71: TERESA | F71: MARLENY | G71: Proveedor
A72: 10802163539 | B72: ALDAVA LEON MARIA ISABEL | C72: MARIA | D72: ISABEL | E72: ALDAVA | F72: LEON | G72: Proveedor
A73: 10009654327 | B73: ALDAVE RAMIREZ VDA DE VILLALOBOS ROSARIO AURORA | C73: ALDAVE | D73: RAMIREZ | E73: ROSARIO | F73: AURORA | G73: Proveedor
A74: 10011172011 | B74: ALEGRIA FERREYRA DORA | C74: ALEGRIA | D74: FERREYRA | E74: DORA | G74: Proveedor
A75: 10000146914 | B75: ALEGRIA MONZON DE FERNANDEZ HILMER | C75: ALEGRIA | D75: MONZON | E75: HILMER | G75: Proveedor
A76: 10400898028 | B76: ALEGRIA PICON JEMSI | C76: ALEGRIA | D76: PICON | E76: JEMSI | G76: Proveedor
A77: 10804230080 | B77: ALEJANDRINA RAMIREZ FLORES | C77: FLORES | D77: RAMIREZ | E77: ALEJANDRINA | G77: Proveedor
A78: 10225142489 | B78: ALEJANDRO ALCEDO AVELINA AURELIA | C78: ALEJANDRO | D78: ALCEDO | E78: AVELINA | F78: AURELIA | G78: Proveedor
A79: 10278458577 | B79: ALEJANDRO SILVA ALTAMIRANO | C79: ALEJANDRO | D79: SILVA | E79: ALTAMIRANO | G79: Proveedor
A80: 10434949551 | B80: ALEJO SACRAMENTO EMILIO | C80: ALEJO | D80: SACRAMENTO | E80: EMILIO | G80: Proveedor
A81: 10484527941 | B81: ALEX ANDERSON TORRES HUANASCA | C81: ALEX | D81: ANDERSON | E81: TORRES | F81: HUANASCA | G81: Proveedor
A82: 17202412092 | B82: ALFARO VDA.DE CHUQUIMANTARI FANNY DOMITILA | C82: ALFARO | D82: VDA DE CHUQUIMANTARI | E82: FANNY | F82: DOMITILA | G82: Proveedor
A83: 10000082096 | B83: ALFREDO DIAZ RAMIREZ | C83: ALFREDO | D83: DIAZ | E83: RAMIREZ | G83: Proveedor
A84: 20606450541 | B84: ALIANZA FERRETERA E.I.R.L. | G84: Proveedor
A85: 10277022287 | B85: ALICIA MONDRAGON PEDRAZA | C85: ALICIA | D85: MONDRAGON | E85: PEDRAZA | G85: Proveedor
A86: 10008169522 | B86: ALIDA DIAZ DE CELIS | C86: ALIDA | D86: DIAZ | E86: DE | F86: CELIS | G86: Proveedor
A87: 20606144122 | B87: ALIMENTOS ANDINOS AMAZONICOS SOCIEDAD ANONIMA CERRADA | G87: Proveedor
A88: 20561204676 | B88: ALIMENTOS Y BEBIDAS EL MINI E.I.R.L. | G88: Proveedor
A89: 10001199914 | B89: ALIX RIOS RIOS | C89: ALIX | D89: RIOS | E89: RIOS | G89: Proveedor
A90: 20393062801 | B90: ALMAPEL E.I.R.L. | G90: Proveedor
A91: 10402225209 | B91: ALTAMIRANO BENAVIDES ELISA MARIBEL | C91: ALTAMIRANO | D91: BENAVIDES | E91: ELISA | F91: MARIBEL | G91: Proveedor
A92: 10475404977 | B92: ALTAMIRANO CERNA ROSITA NANCY | C92: ROSITA | D92: NANCY | E92: ALTAMIRANO | F92: CERNA | G92: Proveedor
A93: 10473045341 | B93: ALTAMIRANO ROJAS MARIA DOLORES | C93: MARIA | D93: DOLORES | E93: ALTAMIRANO | F93: ROJAS | G93: Proveedor
A94: 10010590260 | B94: ALVA BURGA EDIS DARWIN | C94: ALVA | D94: BURGA | E94: EDIS | F94: DARWIN | G94: Proveedor
A95: 10802595919 | B95: ALVARADO CHAVEZ ERNESTO LUQUE | C95: ALVARADO | D95: CHAVEZ | E95: ERNESTO | F95: LUQUE | G95: Proveedor
A96: 10225069153 | B96: ALVARADO GOMEZ JORGE LUIS | C96: ALVARADO | D96: GOMEZ | E96: JORGE | F96: LUIS | G96: Proveedor
A97: 10414446448 | B97: ALVARADO GOMEZ LUIS ANTONIO | C97: ALVARADO | D97: GOMEZ | E97: LUIS | F97: ANTONIO | G97: Proveedor
A98: 10419937491 | B98: ALVARADO ORTIZ RUBEN ANTONIO | C98: ALVARADO | D98: ORTIZ | E98: RUBEN | F98: ANTONIO | G98: Proveedor
A99: 10442757874 | B99: ALVARADO VILCA BELLA LUZ | C99: ALVARADO | D99: VILCA | E99: BELLA | F99: LUZ | G99: Proveedor
A100: 10415674533 | B100: ALVARADO ZORRILLA ROLANDO WILFREDO | C100: ALVARADO | D100: ZORRILLA | E100: ROLANDO | F100: WILFREDO | G100: Proveedor
...
